data_loader/__init__.py
data_loader/core.py
lrp/__init__.py
lrp/builtin.py
lrp/core.py
lrp/filter.py
lrp/image.py
lrp/norm.py
lrp/plot.py
lrp/rules.py
lrp/types.py
lrp/zennit/__init__.py
lrp/zennit/core.py
lrp/zennit/types.py
pf/__init__.py
pf/convert_img.py
pf/core.py
pf/decorators.py
pf/metrics.py
pf/plot.py
pf/sanity_checks.py
pf/utils.py
pf/objectives/__init__.py
pf/objectives/constants.py
pf/objectives/sort.py
pf/perturbation_modes/__init__.py
pf/perturbation_modes/constants.py
pf/perturbation_modes/inpainting/__init__.py
pf/perturbation_modes/inpainting/flip.py
pf/perturbation_modes/random/__init__.py
pf/perturbation_modes/random/flip.py
pf/perturbation_modes/random/random_number_generators.py
lrp_pf_auc-0.1.6.dist-info/METADATA
lrp_pf_auc-0.1.6.dist-info/WHEEL
lrp_pf_auc-0.1.6.dist-info/license
lrp_pf_auc-0.1.6.dist-info/top_level.txt
lrp_pf_auc-0.1.6.dist-info/RECORD
