Metadata-Version: 2.1
Name: lrp-pf-auc
Version: 0.1.6
Summary: Explain Neural Networks using Layer-Wise Relevance Propagation and evaluate the explanations using Pixel-Flipping and Area Under the Curve.
Home-page: https://github.com/rodrigobdz/lrp
Author: rodrigobdz
Author-email: r.bermudezschettino@campus.tu-berlin.de
Maintainer: rodrigobdz
Maintainer-email: r.bermudezschettino@campus.tu-berlin.de
License: MIT
Classifier: Development Status :: 3 - Alpha
Classifier: Environment :: GPU
Classifier: Framework :: IPython
Classifier: Framework :: Jupyter
Classifier: Intended Audience :: Developers
Classifier: Intended Audience :: Education
Classifier: Intended Audience :: Science/Research
Classifier: License :: OSI Approved :: MIT License
Classifier: Programming Language :: Python
Classifier: Programming Language :: Python :: 3
Classifier: Programming Language :: Python :: 3 :: Only
Classifier: Programming Language :: Python :: 3.9
Classifier: Programming Language :: Python :: 3.10
Classifier: Topic :: Scientific/Engineering :: Artificial Intelligence
Classifier: Topic :: Scientific/Engineering :: Image Processing
Classifier: Topic :: Scientific/Engineering :: Image Recognition
Classifier: Topic :: Scientific/Engineering :: Mathematics
Classifier: Topic :: Software Development :: Libraries :: Python Modules
Classifier: Typing :: Typed
Requires-Python: >=3.9
License-File: license
Requires-Dist: matplotlib
Requires-Dist: numpy
Requires-Dist: opencv-contrib-python-headless
Requires-Dist: scikit-learn
Requires-Dist: torch (>=1.10.0)
Requires-Dist: torchvision (>=0.11.1)
Provides-Extra: dev
Requires-Dist: autopep8 (>=1.6.0) ; extra == 'dev'
Requires-Dist: build (>=0.7.0) ; extra == 'dev'
Requires-Dist: ipykernel (>=6.6.0) ; extra == 'dev'
Requires-Dist: mypy (>=0.920) ; extra == 'dev'
Requires-Dist: notebook (>=6.4.11) ; extra == 'dev'
Requires-Dist: pydocstyle (>=6.1.1) ; extra == 'dev'
Requires-Dist: pylint (>=2.13.8) ; extra == 'dev'
Requires-Dist: scipy (>=1.7.3) ; extra == 'dev'
Requires-Dist: twine (>=4.0.1) ; extra == 'dev'
